{
    "levels": {
        "1": [
            {
                "item_cost": {
                    "item": "create:haunted_bell",
                    "count": 1
                }
            }
        ],
        "2": [
            {
                "item_cost": {
                    "item": "malum:eldritch_spirit",
                    "count": 6
                }
            }
        ],
        "3": [
            {
                "item_cost": {
                    "item": "malum:imitation_flesh",
                    "count": 2
                }
            }
        ]
    }
}