{
  "type": "minecraft:generic",
  "pools": [
    {
      "rolls": 1,
      "entries": [
        {
          "type": "minecraft:item",
          "name": "minecraft:potion",
          "weight": 12,
          "functions": [
            {
              "function": "minecraft:set_potion",
              "id": "minecraft:long_water_breathing"
            }
          ]
        },
        {
          "type": "minecraft:item",
          "name": "minecraft:potion",
          "weight": 12,
          "functions": [
            {
              "function": "minecraft:set_potion",
              "id": "kobolds:amethyst"
            }
          ]
        },
        {
          "type": "minecraft:item",
          "name": "minecraft:potion",
          "weight": 12,
          "functions": [
            {
              "function": "minecraft:set_potion",
              "id": "minecraft:long_fire_resistance"
            }
          ]
        },
        {
          "type": "minecraft:item",
          "name": "minecraft:book",
          "weight": 4,
          "functions": [
            {
              "function": "minecraft:enchant_randomly",
              "options": "kobolds:prospector"
            }
          ]
        },
        {
          "type": "minecraft:item",
          "name": "minecraft:potion",
          "weight": 2,
          "functions": [
            {
              "function": "minecraft:set_potion",
              "id": "minecraft:luck"
            }
          ]
        }
      ]
    }
  ]
}