{
  "type": "malum:spirit_repair",
  "durabilityPercentage": 1.0,
  "repairMaterial": {
    "count": 2,
    "item": "malum:cthonic_gold_fragment"
  },
  "spirits": [
    {
      "type": "malum:aqueous",
      "count": 8
    },
    {
      "type": "malum:infernal",
      "count": 8
    }
  ],
  "validItems": [
    "malum:fractured_aluminum_impetus",
    "malum:fractured_copper_impetus",
    "malum:fractured_gold_impetus",
    "malum:fractured_iron_impetus",
    "malum:fractured_lead_impetus",
    "malum:fractured_nickel_impetus",
    "malum:fractured_zinc_impetus"
  ]
}